<?xml version="1.0" encoding="UTF-8"?>
<gml:Dictionary xmlns:gml="http://www.opengis.net/gml/3.2" xmlns:xsi="http://www.w3.org/2001/XMLSchema-instance" gml:id="3c111437-6440-45f6-9434-8f81cd7be925" xsi:schemaLocation="http://www.opengis.net/gml/3.2 null">
	<gml:metaDataDictionary>
		<gml:GenericMetaData>
			<NVDB_ID xsi:type="gml:StringOrRefType"></NVDB_ID>
			<status xsi:type="gml:StringOrRefType">Sendt inn</status>
			<kilde xsi:type="gml:StringOrRefType">Håndboka/NVDB/SOSI</kilde>
		</gml:GenericMetaData>
	</gml:metaDataDictionary>
	<gml:identifier codeSpace="https://raw.githubusercontent.com/Arkitektum/UML-modellering-VU053/main/codelists/fmv_Material.xml">Material</gml:identifier>
	<gml:dictionaryEntry>
		<gml:Definition gml:id="_2393_7423">
			<gml:description></gml:description>
			<gml:metaDataProperty>
				<gml:GenericMetaData>
					<NVDB_ID xsi:type="gml:StringOrRefType"></NVDB_ID>
				</gml:GenericMetaData>
			</gml:metaDataProperty>
			<gml:identifier codeSpace="https://raw.githubusercontent.com/Arkitektum/UML-modellering-VU053/main/codelists/fmv_Material.xml">gress</gml:identifier>
		</gml:Definition>
	</gml:dictionaryEntry>
	<gml:dictionaryEntry>
		<gml:Definition gml:id="_2393_7424">
			<gml:description></gml:description>
			<gml:metaDataProperty>
				<gml:GenericMetaData>
					<NVDB_ID xsi:type="gml:StringOrRefType"></NVDB_ID>
				</gml:GenericMetaData>
			</gml:metaDataProperty>
			<gml:identifier codeSpace="https://raw.githubusercontent.com/Arkitektum/UML-modellering-VU053/main/codelists/fmv_Material.xml">grus</gml:identifier>
		</gml:Definition>
	</gml:dictionaryEntry>
	<gml:dictionaryEntry>
		<gml:Definition gml:id="_2393_7425">
			<gml:description></gml:description>
			<gml:metaDataProperty>
				<gml:GenericMetaData>
					<NVDB_ID xsi:type="gml:StringOrRefType"></NVDB_ID>
				</gml:GenericMetaData>
			</gml:metaDataProperty>
			<gml:identifier codeSpace="https://raw.githubusercontent.com/Arkitektum/UML-modellering-VU053/main/codelists/fmv_Material.xml">asfalt</gml:identifier>
		</gml:Definition>
	</gml:dictionaryEntry>
	<gml:dictionaryEntry>
		<gml:Definition gml:id="_2393_7426">
			<gml:description></gml:description>
			<gml:metaDataProperty>
				<gml:GenericMetaData>
					<NVDB_ID xsi:type="gml:StringOrRefType"></NVDB_ID>
				</gml:GenericMetaData>
			</gml:metaDataProperty>
			<gml:identifier codeSpace="https://raw.githubusercontent.com/Arkitektum/UML-modellering-VU053/main/codelists/fmv_Material.xml">gatestein / heller</gml:identifier>
		</gml:Definition>
	</gml:dictionaryEntry>
	<gml:dictionaryEntry>
		<gml:Definition gml:id="_2393_7427">
			<gml:description></gml:description>
			<gml:metaDataProperty>
				<gml:GenericMetaData>
					<NVDB_ID xsi:type="gml:StringOrRefType"></NVDB_ID>
				</gml:GenericMetaData>
			</gml:metaDataProperty>
			<gml:identifier codeSpace="https://raw.githubusercontent.com/Arkitektum/UML-modellering-VU053/main/codelists/fmv_Material.xml">betong</gml:identifier>
		</gml:Definition>
	</gml:dictionaryEntry>
	<gml:dictionaryEntry>
		<gml:Definition gml:id="_2393_7428">
			<gml:description></gml:description>
			<gml:metaDataProperty>
				<gml:GenericMetaData>
					<NVDB_ID xsi:type="gml:StringOrRefType"></NVDB_ID>
				</gml:GenericMetaData>
			</gml:metaDataProperty>
			<gml:identifier codeSpace="https://raw.githubusercontent.com/Arkitektum/UML-modellering-VU053/main/codelists/fmv_Material.xml">naturstein</gml:identifier>
		</gml:Definition>
	</gml:dictionaryEntry>
</gml:Dictionary>
